nmpy.py
nmpy-0.0.1.dist-info/METADATA
nmpy-0.0.1.dist-info/WHEEL
nmpy-0.0.1.dist-info/top_level.txt
nmpy-0.0.1.dist-info/RECORD
