Metadata-Version: 2.1
Name: nmpy
Version: 0.0.1
Summary: A numpy replacement
Home-page: UNKNOWN
Author: Q
Author-email: 
License: UNKNOWN
Platform: UNKNOWN
Classifier: Programming Language :: Python :: 3
Classifier: License :: OSI Approved :: MIT License
Classifier: Operating System :: OS Independent
Requires-Python: >=3.6
